<manifest alg="2" build="2017.0.0.363" opt="true" iceEnabled="true" iceMarkupVersion="2" iceEnabledOptions="link,responsive,cachebuster" exportTarget="other" domain="www.coloquiodemodateste.com.br" resolutions="1x,2x" timestamp="1484280434830">
  <folder name="css">
    <file name="site_global.css" crc="443350757"/>
    <file name="master_a-mestre.css" crc="188841296" ref="modelo-ic:programação:inscrições:histórico:modelo-gt:comitês-cient:ouvinte:como-chegar:evento:editais:datas:presidências:anais:concurso:submissões:organização:abepem:ic:co:dobras:gt:modelo-co:index"/>
    <file name="nomq_preview_master_a-mestre.css" crc="3824530138" ref="modelo-ic:programação:inscrições:histórico:modelo-gt:comitês-cient:ouvinte:como-chegar:evento:editais:datas:presidências:anais:concurso:submissões:organização:abepem:ic:co:dobras:gt:modelo-co:index"/>
    <file name="modelo-ic.css" crc="3971277381" ref="modelo-ic"/>
    <file name="nomq_modelo-ic.css" crc="457382950" ref="modelo-ic"/>
    <file name="programa__o.css" crc="4089769834" ref="programação"/>
    <file name="nomq_programa__o.css" crc="3986199716" ref="programação"/>
    <file name="inscri__es.css" crc="4102651035" ref="inscrições"/>
    <file name="nomq_inscri__es.css" crc="279247440" ref="inscrições"/>
    <file name="hist_rico.css" crc="3829804891" ref="histórico"/>
    <file name="nomq_hist_rico.css" crc="3816193382" ref="histórico"/>
    <file name="modelo-gt.css" crc="3797573432" ref="modelo-gt"/>
    <file name="nomq_modelo-gt.css" crc="4052685389" ref="modelo-gt"/>
    <file name="comit_s-cient.css" crc="143854082" ref="comitês-cient"/>
    <file name="nomq_comit_s-cient.css" crc="138320066" ref="comitês-cient"/>
    <file name="ouvinte.css" crc="252001441" ref="ouvinte"/>
    <file name="nomq_ouvinte.css" crc="507408201" ref="ouvinte"/>
    <file name="como-chegar.css" crc="3998794573" ref="como-chegar"/>
    <file name="nomq_como-chegar.css" crc="4064299816" ref="como-chegar"/>
    <file name="evento.css" crc="3806193262" ref="evento"/>
    <file name="nomq_evento.css" crc="536696409" ref="evento"/>
    <file name="editais.css" crc="199066407" ref="editais"/>
    <file name="nomq_editais.css" crc="4278120923" ref="editais"/>
    <file name="datas.css" crc="3437045" ref="datas"/>
    <file name="nomq_datas.css" crc="4081200516" ref="datas"/>
    <file name="presid_ncias.css" crc="4095531539" ref="presidências"/>
    <file name="nomq_presid_ncias.css" crc="3911256851" ref="presidências"/>
    <file name="anais.css" crc="4009494112" ref="anais"/>
    <file name="nomq_anais.css" crc="4238069664" ref="anais"/>
    <file name="concurso.css" crc="524629665" ref="concurso"/>
    <file name="nomq_concurso.css" crc="470918478" ref="concurso"/>
    <file name="submiss_es.css" crc="4008413739" ref="submissões"/>
    <file name="nomq_submiss_es.css" crc="50241032" ref="submissões"/>
    <file name="organiza__o.css" crc="4210002064" ref="organização"/>
    <file name="nomq_organiza__o.css" crc="73453757" ref="organização"/>
    <file name="abepem.css" crc="254972174" ref="abepem"/>
    <file name="nomq_abepem.css" crc="4192352235" ref="abepem"/>
    <file name="ic.css" crc="181248355" ref="ic"/>
    <file name="nomq_ic.css" crc="132908641" ref="ic"/>
    <file name="co.css" crc="213819838" ref="co"/>
    <file name="nomq_co.css" crc="279668286" ref="co"/>
    <file name="dobras.css" crc="4260119775" ref="dobras"/>
    <file name="nomq_dobras.css" crc="146586398" ref="dobras"/>
    <file name="gt.css" crc="3775431781" ref="gt"/>
    <file name="nomq_gt.css" crc="392611748" ref="gt"/>
    <file name="modelo-co.css" crc="143670683" ref="modelo-co"/>
    <file name="nomq_modelo-co.css" crc="4063544904" ref="modelo-co"/>
    <file name="index.css" crc="103965264" ref="index"/>
    <file name="nomq_index.css" crc="224281914" ref="index"/>
  </folder>
  <folder name="scripts">
    <file name="jquery-1.8.3.min.js" crc="209076791" ref="index:inscrições:ouvinte:datas:submissões:ic:gt:modelo-ic:modelo-gt:evento:anais:dobras:histórico:como-chegar:presidências:organização:co:modelo-co:programação:comitês-cient:editais:concurso:abepem"/>
    <file name="museutils.js" crc="163421577" ref="index:inscrições:ouvinte:datas:submissões:ic:gt:modelo-ic:modelo-gt:evento:anais:dobras:histórico:como-chegar:presidências:organização:co:modelo-co:programação:comitês-cient:editais:concurso:abepem"/>
    <file name="whatinput.js" crc="86476730" ref="index:inscrições:ouvinte:datas:submissões:ic:gt:modelo-ic:modelo-gt:evento:anais:dobras:histórico:como-chegar:presidências:organização:co:modelo-co:programação:comitês-cient:editais:concurso:abepem"/>
    <file name="museconfig.js" crc="36584860" ref="index:inscrições:ouvinte:datas:submissões:ic:gt:modelo-ic:modelo-gt:evento:anais:dobras:histórico:como-chegar:presidências:organização:co:modelo-co:programação:comitês-cient:editais:concurso:abepem"/>
    <file name="jquery.musemenu.js" crc="146495465" ref="index:inscrições:ouvinte:datas:submissões:ic:gt:modelo-ic:modelo-gt:evento:anais:dobras:histórico:como-chegar:presidências:organização:co:modelo-co:programação:comitês-cient:editais:concurso:abepem"/>
    <file name="jquery.watch.js" crc="104486786" ref="index:inscrições:ouvinte:datas:submissões:ic:gt:modelo-ic:modelo-gt:evento:anais:dobras:histórico:como-chegar:presidências:organização:co:modelo-co:programação:comitês-cient:editais:concurso:abepem"/>
    <file name="webpro.js" crc="3848665353" ref="index:inscrições:ouvinte:datas:submissões:ic:gt:modelo-ic:modelo-gt:evento:anais:dobras:histórico:como-chegar:presidências:organização:co:modelo-co:programação:comitês-cient:editais:concurso:abepem"/>
    <file name="musewpslideshow.js" crc="4041717617" ref="index"/>
    <file name="jquery.museoverlay.js" crc="36492500" ref="index"/>
    <file name="touchswipe.js" crc="404375771" ref="index"/>
    <file name="form_check.php" crc="158155501" ref="index"/>
    <file name="form_throttle.php" crc="3992970984" ref="index"/>
    <file name="form_process.php" crc="4078697226" ref="index"/>
    <file name="form-u8529.php" crc="5679986" ref="index"/>
    <file name="html5shiv.js" crc="4241844378" ref="index:inscrições:ouvinte:datas:submissões:ic:gt:modelo-ic:modelo-gt:evento:anais:dobras:histórico:como-chegar:presidências:organização:co:modelo-co:programação:comitês-cient:editais:concurso:abepem"/>
    <file name="jquery.museresponsive.js" crc="4146931122" ref="index:inscrições:ouvinte:datas:submissões:ic:gt:modelo-ic:modelo-gt:evento:anais:dobras:histórico:como-chegar:presidências:organização:co:modelo-co:programação:comitês-cient:editais:concurso:abepem"/>
    <file name="require.js" crc="244322403" ref="index:inscrições:ouvinte:datas:submissões:ic:gt:modelo-ic:modelo-gt:evento:anais:dobras:histórico:como-chegar:presidências:organização:co:modelo-co:programação:comitês-cient:editais:concurso:abepem"/>
  </folder>
  <folder name="images">
    <file name="header 1-flor-do-cerrado-1920x1080.png" crc="413959362" seo="true" ref="index:inscrições:ouvinte:datas:submissões:ic:gt:modelo-ic:modelo-gt:evento:anais:dobras:histórico:como-chegar:presidências:organização:co:modelo-co:programação:comitês-cient:editais:concurso:abepem"/>
    <file name="blank.gif" crc="4208392903" ref="index:inscrições:ouvinte:datas:submissões:ic:gt:modelo-ic:modelo-gt:evento:anais:dobras:histórico:como-chegar:presidências:organização:co:modelo-co:programação:comitês-cient:editais:concurso:abepem"/>
    <file name="u6222.png" crc="258678038" ref="index:inscrições:ouvinte:datas:submissões:ic:gt:modelo-ic:modelo-gt:evento:anais:dobras:histórico:como-chegar:presidências:organização:co:modelo-co:programação:comitês-cient:editais:concurso:abepem"/>
    <file name="u6222_2x.png" crc="3784976358" ref="index:inscrições:ouvinte:datas:submissões:ic:gt:modelo-ic:modelo-gt:evento:anais:dobras:histórico:como-chegar:presidências:organização:co:modelo-co:programação:comitês-cient:editais:concurso:abepem"/>
    <file name="u6222-r.png" crc="4099970016" ref="index:inscrições:ouvinte:datas:submissões:ic:gt:modelo-ic:modelo-gt:evento:anais:dobras:histórico:como-chegar:presidências:organização:co:modelo-co:programação:comitês-cient:editais:concurso:abepem"/>
    <file name="u6222-r_2x.png" crc="443940961" ref="index:inscrições:ouvinte:datas:submissões:ic:gt:modelo-ic:modelo-gt:evento:anais:dobras:histórico:como-chegar:presidências:organização:co:modelo-co:programação:comitês-cient:editais:concurso:abepem"/>
    <file name="u6222-m.png" crc="3912827430" ref="index:inscrições:ouvinte:datas:submissões:ic:gt:modelo-ic:modelo-gt:evento:anais:dobras:histórico:como-chegar:presidências:organização:co:modelo-co:programação:comitês-cient:editais:concurso:abepem"/>
    <file name="u6222-m_2x.png" crc="254151367" ref="index:inscrições:ouvinte:datas:submissões:ic:gt:modelo-ic:modelo-gt:evento:anais:dobras:histórico:como-chegar:presidências:organização:co:modelo-co:programação:comitês-cient:editais:concurso:abepem"/>
    <file name="u6472.png" crc="4167447177" ref="index:inscrições:ouvinte:datas:submissões:ic:gt:modelo-ic:modelo-gt:evento:anais:dobras:histórico:como-chegar:presidências:organização:co:modelo-co:programação:comitês-cient:editais:concurso:abepem"/>
    <file name="u6472_2x.png" crc="3982193251" ref="index:inscrições:ouvinte:datas:submissões:ic:gt:modelo-ic:modelo-gt:evento:anais:dobras:histórico:como-chegar:presidências:organização:co:modelo-co:programação:comitês-cient:editais:concurso:abepem"/>
    <file name="u6472-r.png" crc="219177008" ref="index:inscrições:ouvinte:datas:submissões:ic:gt:modelo-ic:modelo-gt:evento:anais:dobras:histórico:como-chegar:presidências:organização:co:modelo-co:programação:comitês-cient:editais:concurso:abepem"/>
    <file name="u6472-r_2x.png" crc="345739671" ref="index:inscrições:ouvinte:datas:submissões:ic:gt:modelo-ic:modelo-gt:evento:anais:dobras:histórico:como-chegar:presidências:organização:co:modelo-co:programação:comitês-cient:editais:concurso:abepem"/>
    <file name="u6472-m.png" crc="3905308943" ref="index:inscrições:ouvinte:datas:submissões:ic:gt:modelo-ic:modelo-gt:evento:anais:dobras:histórico:como-chegar:presidências:organização:co:modelo-co:programação:comitês-cient:editais:concurso:abepem"/>
    <file name="u6472-m_2x.png" crc="421651198" ref="index:inscrições:ouvinte:datas:submissões:ic:gt:modelo-ic:modelo-gt:evento:anais:dobras:histórico:como-chegar:presidências:organização:co:modelo-co:programação:comitês-cient:editais:concurso:abepem"/>
    <file name="arrowmenudown.png" crc="262559161" ref="index"/>
    <file name="u8081.png" crc="3944075204" ref="index:inscrições:ouvinte:datas:submissões:ic:gt:modelo-ic:modelo-gt:evento:anais:dobras:histórico:como-chegar:presidências:organização:co:modelo-co:programação:comitês-cient:editais:concurso:abepem"/>
    <file name="u8081_2x.png" crc="455377166" ref="index:inscrições:ouvinte:datas:submissões:ic:gt:modelo-ic:modelo-gt:evento:anais:dobras:histórico:como-chegar:presidências:organização:co:modelo-co:programação:comitês-cient:editais:concurso:abepem"/>
    <file name="u8081-m.png" crc="3787358091" ref="index:inscrições:ouvinte:datas:submissões:ic:gt:modelo-ic:modelo-gt:evento:anais:dobras:histórico:como-chegar:presidências:organização:co:modelo-co:programação:comitês-cient:editais:concurso:abepem"/>
    <file name="u8081-m_2x.png" crc="246679077" ref="index:inscrições:ouvinte:datas:submissões:ic:gt:modelo-ic:modelo-gt:evento:anais:dobras:histórico:como-chegar:presidências:organização:co:modelo-co:programação:comitês-cient:editais:concurso:abepem"/>
    <file name="u8114.png" crc="524850192" ref="index:inscrições:ouvinte:datas:submissões:ic:gt:modelo-ic:modelo-gt:evento:anais:dobras:histórico:como-chegar:presidências:organização:co:modelo-co:programação:comitês-cient:editais:concurso:abepem"/>
    <file name="u8114_2x.png" crc="239499408" ref="index:inscrições:ouvinte:datas:submissões:ic:gt:modelo-ic:modelo-gt:evento:anais:dobras:histórico:como-chegar:presidências:organização:co:modelo-co:programação:comitês-cient:editais:concurso:abepem"/>
    <file name="u8114-m.png" crc="4143935523" ref="index:inscrições:ouvinte:datas:submissões:ic:gt:modelo-ic:modelo-gt:evento:anais:dobras:histórico:como-chegar:presidências:organização:co:modelo-co:programação:comitês-cient:editais:concurso:abepem"/>
    <file name="u8114-m_2x.png" crc="3795635191" ref="index:inscrições:ouvinte:datas:submissões:ic:gt:modelo-ic:modelo-gt:evento:anais:dobras:histórico:como-chegar:presidências:organização:co:modelo-co:programação:comitês-cient:editais:concurso:abepem"/>
    <file name="u6749.png" crc="65161761" ref="index:inscrições:ouvinte:datas:submissões:ic:gt:modelo-ic:modelo-gt:evento:anais:dobras:histórico:como-chegar:presidências:organização:co:modelo-co:programação:comitês-cient:editais:concurso:abepem"/>
    <file name="u6749_2x.png" crc="3845949635" ref="index:inscrições:ouvinte:datas:submissões:ic:gt:modelo-ic:modelo-gt:evento:anais:dobras:histórico:como-chegar:presidências:organização:co:modelo-co:programação:comitês-cient:editais:concurso:abepem"/>
    <file name="u6749-r.png" crc="4216556595" ref="index:inscrições:ouvinte:datas:submissões:ic:gt:modelo-ic:modelo-gt:evento:anais:dobras:histórico:como-chegar:presidências:organização:co:modelo-co:programação:comitês-cient:editais:concurso:abepem"/>
    <file name="u6749-r_2x.png" crc="3935909846" ref="index:inscrições:ouvinte:datas:submissões:ic:gt:modelo-ic:modelo-gt:evento:anais:dobras:histórico:como-chegar:presidências:organização:co:modelo-co:programação:comitês-cient:editais:concurso:abepem"/>
    <file name="u6749-m.png" crc="3996508891" ref="index:inscrições:ouvinte:datas:submissões:ic:gt:modelo-ic:modelo-gt:evento:anais:dobras:histórico:como-chegar:presidências:organização:co:modelo-co:programação:comitês-cient:editais:concurso:abepem"/>
    <file name="u6749-m_2x.png" crc="456484737" ref="index:inscrições:ouvinte:datas:submissões:ic:gt:modelo-ic:modelo-gt:evento:anais:dobras:histórico:como-chegar:presidências:organização:co:modelo-co:programação:comitês-cient:editais:concurso:abepem"/>
    <file name="u6735.png" crc="4123165742" ref="index:inscrições:ouvinte:datas:submissões:ic:gt:modelo-ic:modelo-gt:evento:anais:dobras:histórico:como-chegar:presidências:organização:co:modelo-co:programação:comitês-cient:editais:concurso:abepem"/>
    <file name="u6735_2x.png" crc="299618254" ref="index:inscrições:ouvinte:datas:submissões:ic:gt:modelo-ic:modelo-gt:evento:anais:dobras:histórico:como-chegar:presidências:organização:co:modelo-co:programação:comitês-cient:editais:concurso:abepem"/>
    <file name="u6735-r.png" crc="4123165742" ref="index:inscrições:ouvinte:datas:submissões:ic:gt:modelo-ic:modelo-gt:evento:anais:dobras:histórico:como-chegar:presidências:organização:co:modelo-co:programação:comitês-cient:editais:concurso:abepem"/>
    <file name="u6735-r_2x.png" crc="299618254" ref="index:inscrições:ouvinte:datas:submissões:ic:gt:modelo-ic:modelo-gt:evento:anais:dobras:histórico:como-chegar:presidências:organização:co:modelo-co:programação:comitês-cient:editais:concurso:abepem"/>
    <file name="u6735-m.png" crc="90081335" ref="index:inscrições:ouvinte:datas:submissões:ic:gt:modelo-ic:modelo-gt:evento:anais:dobras:histórico:como-chegar:presidências:organização:co:modelo-co:programação:comitês-cient:editais:concurso:abepem"/>
    <file name="u6735-m_2x.png" crc="57833023" ref="index:inscrições:ouvinte:datas:submissões:ic:gt:modelo-ic:modelo-gt:evento:anais:dobras:histórico:como-chegar:presidências:organização:co:modelo-co:programação:comitês-cient:editais:concurso:abepem"/>
    <file name="u6735-a.png" crc="4123165742" ref="index:inscrições:ouvinte:datas:submissões:ic:gt:modelo-ic:modelo-gt:evento:anais:dobras:histórico:como-chegar:presidências:organização:co:modelo-co:programação:comitês-cient:editais:concurso:abepem"/>
    <file name="u6735-a_2x.png" crc="299618254" ref="index:inscrições:ouvinte:datas:submissões:ic:gt:modelo-ic:modelo-gt:evento:anais:dobras:histórico:como-chegar:presidências:organização:co:modelo-co:programação:comitês-cient:editais:concurso:abepem"/>
    <file name="u49308.png" crc="3875588062" ref="index:inscrições:ouvinte:datas:submissões:ic:gt:modelo-ic:modelo-gt:evento:anais:dobras:histórico:como-chegar:presidências:organização:co:modelo-co:programação:comitês-cient:editais:concurso:abepem"/>
    <file name="u49308_2x.png" crc="476973028" ref="index:inscrições:ouvinte:datas:submissões:ic:gt:modelo-ic:modelo-gt:evento:anais:dobras:histórico:como-chegar:presidências:organização:co:modelo-co:programação:comitês-cient:editais:concurso:abepem"/>
    <file name="u49308-r.png" crc="3875588062" ref="index:inscrições:ouvinte:datas:submissões:ic:gt:modelo-ic:modelo-gt:evento:anais:dobras:histórico:como-chegar:presidências:organização:co:modelo-co:programação:comitês-cient:editais:concurso:abepem"/>
    <file name="u49308-r_2x.png" crc="476973028" ref="index:inscrições:ouvinte:datas:submissões:ic:gt:modelo-ic:modelo-gt:evento:anais:dobras:histórico:como-chegar:presidências:organização:co:modelo-co:programação:comitês-cient:editais:concurso:abepem"/>
    <file name="u49308-m.png" crc="247897112" ref="index:inscrições:ouvinte:datas:submissões:ic:gt:modelo-ic:modelo-gt:evento:anais:dobras:histórico:como-chegar:presidências:organização:co:modelo-co:programação:comitês-cient:editais:concurso:abepem"/>
    <file name="u49308-m_2x.png" crc="3842352692" ref="index:inscrições:ouvinte:datas:submissões:ic:gt:modelo-ic:modelo-gt:evento:anais:dobras:histórico:como-chegar:presidências:organização:co:modelo-co:programação:comitês-cient:editais:concurso:abepem"/>
    <file name="u49308-a.png" crc="3875588062" ref="index:inscrições:ouvinte:datas:submissões:ic:gt:modelo-ic:modelo-gt:evento:anais:dobras:histórico:como-chegar:presidências:organização:co:modelo-co:programação:comitês-cient:editais:concurso:abepem"/>
    <file name="u49308-a_2x.png" crc="476973028" ref="index:inscrições:ouvinte:datas:submissões:ic:gt:modelo-ic:modelo-gt:evento:anais:dobras:histórico:como-chegar:presidências:organização:co:modelo-co:programação:comitês-cient:editais:concurso:abepem"/>
    <file name="u6722.png" crc="4148547719" ref="index:inscrições:ouvinte:datas:submissões:ic:gt:modelo-ic:modelo-gt:evento:anais:dobras:histórico:como-chegar:presidências:organização:co:modelo-co:programação:comitês-cient:editais:concurso:abepem"/>
    <file name="u6722_2x.png" crc="302450711" ref="index:inscrições:ouvinte:datas:submissões:ic:gt:modelo-ic:modelo-gt:evento:anais:dobras:histórico:como-chegar:presidências:organização:co:modelo-co:programação:comitês-cient:editais:concurso:abepem"/>
    <file name="u6722-r.png" crc="4148547719" ref="index:inscrições:ouvinte:datas:submissões:ic:gt:modelo-ic:modelo-gt:evento:anais:dobras:histórico:como-chegar:presidências:organização:co:modelo-co:programação:comitês-cient:editais:concurso:abepem"/>
    <file name="u6722-r_2x.png" crc="302450711" ref="index:inscrições:ouvinte:datas:submissões:ic:gt:modelo-ic:modelo-gt:evento:anais:dobras:histórico:como-chegar:presidências:organização:co:modelo-co:programação:comitês-cient:editais:concurso:abepem"/>
    <file name="u6722-m.png" crc="4019182628" ref="index:inscrições:ouvinte:datas:submissões:ic:gt:modelo-ic:modelo-gt:evento:anais:dobras:histórico:como-chegar:presidências:organização:co:modelo-co:programação:comitês-cient:editais:concurso:abepem"/>
    <file name="u6722-m_2x.png" crc="4204535698" ref="index:inscrições:ouvinte:datas:submissões:ic:gt:modelo-ic:modelo-gt:evento:anais:dobras:histórico:como-chegar:presidências:organização:co:modelo-co:programação:comitês-cient:editais:concurso:abepem"/>
    <file name="u6722-a.png" crc="4148547719" ref="index:inscrições:ouvinte:datas:submissões:ic:gt:modelo-ic:modelo-gt:evento:anais:dobras:histórico:como-chegar:presidências:organização:co:modelo-co:programação:comitês-cient:editais:concurso:abepem"/>
    <file name="u6722-a_2x.png" crc="302450711" ref="index:inscrições:ouvinte:datas:submissões:ic:gt:modelo-ic:modelo-gt:evento:anais:dobras:histórico:como-chegar:presidências:organização:co:modelo-co:programação:comitês-cient:editais:concurso:abepem"/>
    <file name="u51644.png" crc="110909857" ref="index:inscrições:ouvinte:datas:submissões:ic:gt:modelo-ic:modelo-gt:evento:anais:dobras:histórico:como-chegar:presidências:organização:co:modelo-co:programação:comitês-cient:editais:concurso:abepem"/>
    <file name="u51644_2x.png" crc="4150120801" ref="index:inscrições:ouvinte:datas:submissões:ic:gt:modelo-ic:modelo-gt:evento:anais:dobras:histórico:como-chegar:presidências:organização:co:modelo-co:programação:comitês-cient:editais:concurso:abepem"/>
    <file name="u51644-r.png" crc="4132225921" ref="index:inscrições:ouvinte:datas:submissões:ic:gt:modelo-ic:modelo-gt:evento:anais:dobras:histórico:como-chegar:presidências:organização:co:modelo-co:programação:comitês-cient:editais:concurso:abepem"/>
    <file name="u51644-r_2x.png" crc="421625294" ref="index:inscrições:ouvinte:datas:submissões:ic:gt:modelo-ic:modelo-gt:evento:anais:dobras:histórico:como-chegar:presidências:organização:co:modelo-co:programação:comitês-cient:editais:concurso:abepem"/>
    <file name="u51644-m.png" crc="367960035" ref="index:inscrições:ouvinte:datas:submissões:ic:gt:modelo-ic:modelo-gt:evento:anais:dobras:histórico:como-chegar:presidências:organização:co:modelo-co:programação:comitês-cient:editais:concurso:abepem"/>
    <file name="u51644-m_2x.png" crc="3988347032" ref="index:inscrições:ouvinte:datas:submissões:ic:gt:modelo-ic:modelo-gt:evento:anais:dobras:histórico:como-chegar:presidências:organização:co:modelo-co:programação:comitês-cient:editais:concurso:abepem"/>
    <file name="u7223.png" crc="3774597706" ref="index:inscrições:ouvinte:datas:submissões:ic:gt:modelo-ic:modelo-gt:evento:anais:dobras:histórico:como-chegar:presidências:organização:co:modelo-co:programação:comitês-cient:editais:concurso:abepem"/>
    <file name="u7223_2x.png" crc="3760366460" ref="index:inscrições:ouvinte:datas:submissões:ic:gt:modelo-ic:modelo-gt:evento:anais:dobras:histórico:como-chegar:presidências:organização:co:modelo-co:programação:comitês-cient:editais:concurso:abepem"/>
    <file name="u7223-r.png" crc="175404741" ref="index:inscrições:ouvinte:datas:submissões:ic:gt:modelo-ic:modelo-gt:evento:anais:dobras:histórico:como-chegar:presidências:organização:co:modelo-co:programação:comitês-cient:editais:concurso:abepem"/>
    <file name="u7223-r_2x.png" crc="307163415" ref="index:inscrições:ouvinte:datas:submissões:ic:gt:modelo-ic:modelo-gt:evento:anais:dobras:histórico:como-chegar:presidências:organização:co:modelo-co:programação:comitês-cient:editais:concurso:abepem"/>
    <file name="u7223-m.png" crc="3827737374" ref="index:inscrições:ouvinte:datas:submissões:ic:gt:modelo-ic:modelo-gt:evento:anais:dobras:histórico:como-chegar:presidências:organização:co:modelo-co:programação:comitês-cient:editais:concurso:abepem"/>
    <file name="u7223-m_2x.png" crc="139235270" ref="index:inscrições:ouvinte:datas:submissões:ic:gt:modelo-ic:modelo-gt:evento:anais:dobras:histórico:como-chegar:presidências:organização:co:modelo-co:programação:comitês-cient:editais:concurso:abepem"/>
    <file name="u46917.png" crc="201093662" ref="index:inscrições:ouvinte:datas:submissões:ic:gt:modelo-ic:modelo-gt:evento:anais:dobras:histórico:como-chegar:presidências:organização:co:modelo-co:programação:comitês-cient:editais:concurso:abepem"/>
    <file name="u46917_2x.png" crc="4158392772" ref="index:inscrições:ouvinte:datas:submissões:ic:gt:modelo-ic:modelo-gt:evento:anais:dobras:histórico:como-chegar:presidências:organização:co:modelo-co:programação:comitês-cient:editais:concurso:abepem"/>
    <file name="u46917-r.png" crc="201093662" ref="index:inscrições:ouvinte:datas:submissões:ic:gt:modelo-ic:modelo-gt:evento:anais:dobras:histórico:como-chegar:presidências:organização:co:modelo-co:programação:comitês-cient:editais:concurso:abepem"/>
    <file name="u46917-r_2x.png" crc="4158392772" ref="index:inscrições:ouvinte:datas:submissões:ic:gt:modelo-ic:modelo-gt:evento:anais:dobras:histórico:como-chegar:presidências:organização:co:modelo-co:programação:comitês-cient:editais:concurso:abepem"/>
    <file name="u46917-m.png" crc="468421708" ref="index:inscrições:ouvinte:datas:submissões:ic:gt:modelo-ic:modelo-gt:evento:anais:dobras:histórico:como-chegar:presidências:organização:co:modelo-co:programação:comitês-cient:editais:concurso:abepem"/>
    <file name="u46917-m_2x.png" crc="351434984" ref="index:inscrições:ouvinte:datas:submissões:ic:gt:modelo-ic:modelo-gt:evento:anais:dobras:histórico:como-chegar:presidências:organização:co:modelo-co:programação:comitês-cient:editais:concurso:abepem"/>
    <file name="u46917-a.png" crc="201093662" ref="index:inscrições:ouvinte:datas:submissões:ic:gt:modelo-ic:modelo-gt:evento:anais:dobras:histórico:como-chegar:presidências:organização:co:modelo-co:programação:comitês-cient:editais:concurso:abepem"/>
    <file name="u46917-a_2x.png" crc="4158392772" ref="index:inscrições:ouvinte:datas:submissões:ic:gt:modelo-ic:modelo-gt:evento:anais:dobras:histórico:como-chegar:presidências:organização:co:modelo-co:programação:comitês-cient:editais:concurso:abepem"/>
    <file name="u7642.png" crc="431457501" ref="index:inscrições:ouvinte:datas:submissões:ic:gt:modelo-ic:modelo-gt:evento:anais:dobras:histórico:como-chegar:presidências:organização:co:modelo-co:programação:comitês-cient:editais:concurso:abepem"/>
    <file name="u7642_2x.png" crc="4123423709" ref="index:inscrições:ouvinte:datas:submissões:ic:gt:modelo-ic:modelo-gt:evento:anais:dobras:histórico:como-chegar:presidências:organização:co:modelo-co:programação:comitês-cient:editais:concurso:abepem"/>
    <file name="u7642-r.png" crc="431457501" ref="index:inscrições:ouvinte:datas:submissões:ic:gt:modelo-ic:modelo-gt:evento:anais:dobras:histórico:como-chegar:presidências:organização:co:modelo-co:programação:comitês-cient:editais:concurso:abepem"/>
    <file name="u7642-r_2x.png" crc="4123423709" ref="index:inscrições:ouvinte:datas:submissões:ic:gt:modelo-ic:modelo-gt:evento:anais:dobras:histórico:como-chegar:presidências:organização:co:modelo-co:programação:comitês-cient:editais:concurso:abepem"/>
    <file name="u7642-m.png" crc="3878351756" ref="index:inscrições:ouvinte:datas:submissões:ic:gt:modelo-ic:modelo-gt:evento:anais:dobras:histórico:como-chegar:presidências:organização:co:modelo-co:programação:comitês-cient:editais:concurso:abepem"/>
    <file name="u7642-m_2x.png" crc="426042296" ref="index:inscrições:ouvinte:datas:submissões:ic:gt:modelo-ic:modelo-gt:evento:anais:dobras:histórico:como-chegar:presidências:organização:co:modelo-co:programação:comitês-cient:editais:concurso:abepem"/>
    <file name="u7642-a.png" crc="431457501" ref="index:inscrições:ouvinte:datas:submissões:ic:gt:modelo-ic:modelo-gt:evento:anais:dobras:histórico:como-chegar:presidências:organização:co:modelo-co:programação:comitês-cient:editais:concurso:abepem"/>
    <file name="u7642-a_2x.png" crc="4123423709" ref="index:inscrições:ouvinte:datas:submissões:ic:gt:modelo-ic:modelo-gt:evento:anais:dobras:histórico:como-chegar:presidências:organização:co:modelo-co:programação:comitês-cient:editais:concurso:abepem"/>
    <file name="u7475.png" crc="236396724" ref="index:inscrições:ouvinte:datas:submissões:ic:gt:modelo-ic:modelo-gt:evento:anais:dobras:histórico:como-chegar:presidências:organização:co:modelo-co:programação:comitês-cient:editais:concurso:abepem"/>
    <file name="u7475_2x.png" crc="3923337776" ref="index:inscrições:ouvinte:datas:submissões:ic:gt:modelo-ic:modelo-gt:evento:anais:dobras:histórico:como-chegar:presidências:organização:co:modelo-co:programação:comitês-cient:editais:concurso:abepem"/>
    <file name="u7475-r.png" crc="236396724" ref="index:inscrições:ouvinte:datas:submissões:ic:gt:modelo-ic:modelo-gt:evento:anais:dobras:histórico:como-chegar:presidências:organização:co:modelo-co:programação:comitês-cient:editais:concurso:abepem"/>
    <file name="u7475-r_2x.png" crc="3923337776" ref="index:inscrições:ouvinte:datas:submissões:ic:gt:modelo-ic:modelo-gt:evento:anais:dobras:histórico:como-chegar:presidências:organização:co:modelo-co:programação:comitês-cient:editais:concurso:abepem"/>
    <file name="u7475-m.png" crc="194951232" ref="index:inscrições:ouvinte:datas:submissões:ic:gt:modelo-ic:modelo-gt:evento:anais:dobras:histórico:como-chegar:presidências:organização:co:modelo-co:programação:comitês-cient:editais:concurso:abepem"/>
    <file name="u7475-m_2x.png" crc="226323466" ref="index:inscrições:ouvinte:datas:submissões:ic:gt:modelo-ic:modelo-gt:evento:anais:dobras:histórico:como-chegar:presidências:organização:co:modelo-co:programação:comitês-cient:editais:concurso:abepem"/>
    <file name="u7475-a.png" crc="236396724" ref="index:inscrições:ouvinte:datas:submissões:ic:gt:modelo-ic:modelo-gt:evento:anais:dobras:histórico:como-chegar:presidências:organização:co:modelo-co:programação:comitês-cient:editais:concurso:abepem"/>
    <file name="u7475-a_2x.png" crc="3923337776" ref="index:inscrições:ouvinte:datas:submissões:ic:gt:modelo-ic:modelo-gt:evento:anais:dobras:histórico:como-chegar:presidências:organização:co:modelo-co:programação:comitês-cient:editais:concurso:abepem"/>
    <file name="u7442.png" crc="4002474725" ref="index:inscrições:ouvinte:datas:submissões:ic:gt:modelo-ic:modelo-gt:evento:anais:dobras:histórico:como-chegar:presidências:organização:co:modelo-co:programação:comitês-cient:editais:concurso:abepem"/>
    <file name="u7442_2x.png" crc="3823319589" ref="index:inscrições:ouvinte:datas:submissões:ic:gt:modelo-ic:modelo-gt:evento:anais:dobras:histórico:como-chegar:presidências:organização:co:modelo-co:programação:comitês-cient:editais:concurso:abepem"/>
    <file name="u7442-r.png" crc="4002474725" ref="index:inscrições:ouvinte:datas:submissões:ic:gt:modelo-ic:modelo-gt:evento:anais:dobras:histórico:como-chegar:presidências:organização:co:modelo-co:programação:comitês-cient:editais:concurso:abepem"/>
    <file name="u7442-r_2x.png" crc="3823319589" ref="index:inscrições:ouvinte:datas:submissões:ic:gt:modelo-ic:modelo-gt:evento:anais:dobras:histórico:como-chegar:presidências:organização:co:modelo-co:programação:comitês-cient:editais:concurso:abepem"/>
    <file name="u7442-m.png" crc="145223665" ref="index:inscrições:ouvinte:datas:submissões:ic:gt:modelo-ic:modelo-gt:evento:anais:dobras:histórico:como-chegar:presidências:organização:co:modelo-co:programação:comitês-cient:editais:concurso:abepem"/>
    <file name="u7442-m_2x.png" crc="4242846609" ref="index:inscrições:ouvinte:datas:submissões:ic:gt:modelo-ic:modelo-gt:evento:anais:dobras:histórico:como-chegar:presidências:organização:co:modelo-co:programação:comitês-cient:editais:concurso:abepem"/>
    <file name="u7442-a.png" crc="4002474725" ref="index:inscrições:ouvinte:datas:submissões:ic:gt:modelo-ic:modelo-gt:evento:anais:dobras:histórico:como-chegar:presidências:organização:co:modelo-co:programação:comitês-cient:editais:concurso:abepem"/>
    <file name="u7442-a_2x.png" crc="3823319589" ref="index:inscrições:ouvinte:datas:submissões:ic:gt:modelo-ic:modelo-gt:evento:anais:dobras:histórico:como-chegar:presidências:organização:co:modelo-co:programação:comitês-cient:editais:concurso:abepem"/>
    <file name="u7560.png" crc="4250136704" ref="index:inscrições:ouvinte:datas:submissões:ic:gt:modelo-ic:modelo-gt:evento:anais:dobras:histórico:como-chegar:presidências:organização:co:modelo-co:programação:comitês-cient:editais:concurso:abepem"/>
    <file name="u7560_2x.png" crc="4212777159" ref="index:inscrições:ouvinte:datas:submissões:ic:gt:modelo-ic:modelo-gt:evento:anais:dobras:histórico:como-chegar:presidências:organização:co:modelo-co:programação:comitês-cient:editais:concurso:abepem"/>
    <file name="u7560-r.png" crc="4250136704" ref="index:inscrições:ouvinte:datas:submissões:ic:gt:modelo-ic:modelo-gt:evento:anais:dobras:histórico:como-chegar:presidências:organização:co:modelo-co:programação:comitês-cient:editais:concurso:abepem"/>
    <file name="u7560-r_2x.png" crc="4212777159" ref="index:inscrições:ouvinte:datas:submissões:ic:gt:modelo-ic:modelo-gt:evento:anais:dobras:histórico:como-chegar:presidências:organização:co:modelo-co:programação:comitês-cient:editais:concurso:abepem"/>
    <file name="u7560-m.png" crc="3907101272" ref="index:inscrições:ouvinte:datas:submissões:ic:gt:modelo-ic:modelo-gt:evento:anais:dobras:histórico:como-chegar:presidências:organização:co:modelo-co:programação:comitês-cient:editais:concurso:abepem"/>
    <file name="u7560-m_2x.png" crc="3864631664" ref="index:inscrições:ouvinte:datas:submissões:ic:gt:modelo-ic:modelo-gt:evento:anais:dobras:histórico:como-chegar:presidências:organização:co:modelo-co:programação:comitês-cient:editais:concurso:abepem"/>
    <file name="u7560-a.png" crc="4250136704" ref="index:inscrições:ouvinte:datas:submissões:ic:gt:modelo-ic:modelo-gt:evento:anais:dobras:histórico:como-chegar:presidências:organização:co:modelo-co:programação:comitês-cient:editais:concurso:abepem"/>
    <file name="u7560-a_2x.png" crc="4212777159" ref="index:inscrições:ouvinte:datas:submissões:ic:gt:modelo-ic:modelo-gt:evento:anais:dobras:histórico:como-chegar:presidências:organização:co:modelo-co:programação:comitês-cient:editais:concurso:abepem"/>
    <file name="u46067.png" crc="314065702" ref="index:inscrições:ouvinte:datas:submissões:ic:gt:modelo-ic:modelo-gt:evento:anais:dobras:histórico:como-chegar:presidências:organização:co:modelo-co:programação:comitês-cient:editais:concurso:abepem"/>
    <file name="u46067_2x.png" crc="4148246172" ref="index:inscrições:ouvinte:datas:submissões:ic:gt:modelo-ic:modelo-gt:evento:anais:dobras:histórico:como-chegar:presidências:organização:co:modelo-co:programação:comitês-cient:editais:concurso:abepem"/>
    <file name="u46067-r.png" crc="3825450002" ref="index:inscrições:ouvinte:datas:submissões:ic:gt:modelo-ic:modelo-gt:evento:anais:dobras:histórico:como-chegar:presidências:organização:co:modelo-co:programação:comitês-cient:editais:concurso:abepem"/>
    <file name="u46067-r_2x.png" crc="4279065712" ref="index:inscrições:ouvinte:datas:submissões:ic:gt:modelo-ic:modelo-gt:evento:anais:dobras:histórico:como-chegar:presidências:organização:co:modelo-co:programação:comitês-cient:editais:concurso:abepem"/>
    <file name="u46067-m.png" crc="39426694" ref="index:inscrições:ouvinte:datas:submissões:ic:gt:modelo-ic:modelo-gt:evento:anais:dobras:histórico:como-chegar:presidências:organização:co:modelo-co:programação:comitês-cient:editais:concurso:abepem"/>
    <file name="u46067-m_2x.png" crc="3895232600" ref="index:inscrições:ouvinte:datas:submissões:ic:gt:modelo-ic:modelo-gt:evento:anais:dobras:histórico:como-chegar:presidências:organização:co:modelo-co:programação:comitês-cient:editais:concurso:abepem"/>
    <file name="12colo-crop-u8400.png" crc="70475875" ref="index:inscrições:ouvinte:datas:submissões:ic:gt:modelo-ic:modelo-gt:evento:anais:dobras:histórico:como-chegar:presidências:organização:co:modelo-co:programação:comitês-cient:editais:concurso:abepem"/>
    <file name="12colo-crop-u8400_2x.png" crc="3937876066" ref="index:inscrições:ouvinte:datas:submissões:ic:gt:modelo-ic:modelo-gt:evento:anais:dobras:histórico:como-chegar:presidências:organização:co:modelo-co:programação:comitês-cient:editais:concurso:abepem"/>
    <file name="abepem preto.png" crc="3782306563" seo="true" ref="index:inscrições:ouvinte:datas:submissões:ic:gt:modelo-ic:modelo-gt:evento:anais:dobras:histórico:como-chegar:presidências:organização:co:modelo-co:programação:comitês-cient:editais:concurso:abepem"/>
    <file name="u13452-4.png" crc="510861545" ref="index:inscrições:ouvinte:datas:submissões:ic:gt:modelo-ic:modelo-gt:evento:anais:dobras:histórico:como-chegar:presidências:organização:co:modelo-co:programação:comitês-cient:editais:concurso:abepem"/>
    <file name="u13452-4_2x.png" crc="3799115436" ref="index:inscrições:ouvinte:datas:submissões:ic:gt:modelo-ic:modelo-gt:evento:anais:dobras:histórico:como-chegar:presidências:organização:co:modelo-co:programação:comitês-cient:editais:concurso:abepem"/>
    <file name="u48843-4.png" crc="396437993" ref="index:inscrições:ouvinte:datas:submissões:ic:gt:modelo-ic:modelo-gt:evento:anais:dobras:histórico:como-chegar:presidências:organização:co:modelo-co:programação:comitês-cient:editais:concurso:abepem"/>
    <file name="u48843-4_2x.png" crc="535972388" ref="index:inscrições:ouvinte:datas:submissões:ic:gt:modelo-ic:modelo-gt:evento:anais:dobras:histórico:como-chegar:presidências:organização:co:modelo-co:programação:comitês-cient:editais:concurso:abepem"/>
    <file name="unesp pt.png" crc="3941576220" seo="true" ref="index:inscrições:ouvinte:datas:submissões:ic:gt:modelo-ic:modelo-gt:evento:anais:dobras:histórico:como-chegar:presidências:organização:co:modelo-co:programação:comitês-cient:editais:concurso:abepem"/>
    <file name="unesp pt_2x.png" crc="3941576220" seo="true" ref="index:inscrições:ouvinte:datas:submissões:ic:gt:modelo-ic:modelo-gt:evento:anais:dobras:histórico:como-chegar:presidências:organização:co:modelo-co:programação:comitês-cient:editais:concurso:abepem"/>
    <file name="u13440-4.png" crc="4245437482" ref="index"/>
    <file name="u13440-4_2x.png" crc="3883342856" ref="index"/>
    <file name="u13422-4.png" crc="476569997" ref="index"/>
    <file name="u13422-4_2x.png" crc="4073541926" ref="index"/>
    <file name="u13416-4.png" crc="3972334642" ref="index"/>
    <file name="u13416-4_2x.png" crc="4070862190" ref="index"/>
    <file name="u13398-4.png" crc="326304514" ref="index"/>
    <file name="u13398-4_2x.png" crc="46360255" ref="index"/>
    <file name="left.png" crc="208184021" seo="true" ref="index"/>
    <file name="left_2x.png" crc="513343883" seo="true" ref="index"/>
    <file name="right.png" crc="208184021" seo="true" ref="index"/>
    <file name="right_2x.png" crc="513343883" seo="true" ref="index"/>
    <file name="patrocínio.png" crc="4140757849" seo="true" ref="index"/>
    <file name="patrocínio2.png" crc="87711232" seo="true" ref="index"/>
    <file name="loading.gif" crc="3815509949" ref="index"/>
    <file name="u12544-7.png" crc="91660705" ref="index"/>
    <file name="u12544-7_2x.png" crc="3772675900" ref="index"/>
    <file name="ativo 1.png" crc="4259103708" seo="true" ref="index:inscrições:ouvinte:datas:submissões:ic:gt:modelo-ic:modelo-gt:evento:anais:dobras:histórico:como-chegar:presidências:organização:co:modelo-co:programação:comitês-cient:editais:concurso:abepem"/>
    <file name="ativo 1_2x.png" crc="3904147645" seo="true" ref="index:inscrições:ouvinte:datas:submissões:ic:gt:modelo-ic:modelo-gt:evento:anais:dobras:histórico:como-chegar:presidências:organização:co:modelo-co:programação:comitês-cient:editais:concurso:abepem"/>
    <file name="u8603-4.png" crc="3984295709" ref="index:inscrições:ouvinte:datas:submissões:ic:gt:modelo-ic:modelo-gt:evento:anais:dobras:histórico:como-chegar:presidências:organização:co:modelo-co:programação:comitês-cient:editais:concurso:abepem"/>
    <file name="u8603-4_2x.png" crc="3853213743" ref="index:inscrições:ouvinte:datas:submissões:ic:gt:modelo-ic:modelo-gt:evento:anais:dobras:histórico:como-chegar:presidências:organização:co:modelo-co:programação:comitês-cient:editais:concurso:abepem"/>
    <file name="abepem.png" crc="3831861458" seo="true" ref="index:inscrições:ouvinte:datas:submissões:ic:gt:modelo-ic:modelo-gt:evento:anais:dobras:histórico:como-chegar:presidências:organização:co:modelo-co:programação:comitês-cient:editais:concurso:abepem"/>
    <file name="ativo 2.png" crc="62028723" seo="true" ref="index:inscrições:ouvinte:datas:submissões:ic:gt:modelo-ic:modelo-gt:evento:anais:dobras:histórico:como-chegar:presidências:organização:co:modelo-co:programação:comitês-cient:editais:concurso:abepem"/>
    <file name="ativo 2_2x.png" crc="4114220889" seo="true" ref="index:inscrições:ouvinte:datas:submissões:ic:gt:modelo-ic:modelo-gt:evento:anais:dobras:histórico:como-chegar:presidências:organização:co:modelo-co:programação:comitês-cient:editais:concurso:abepem"/>
    <file name="u8607-4.png" crc="391200157" ref="index:inscrições:ouvinte:datas:submissões:ic:gt:modelo-ic:modelo-gt:evento:anais:dobras:histórico:como-chegar:presidências:organização:co:modelo-co:programação:comitês-cient:editais:concurso:abepem"/>
    <file name="u8607-4_2x.png" crc="173235097" ref="index:inscrições:ouvinte:datas:submissões:ic:gt:modelo-ic:modelo-gt:evento:anais:dobras:histórico:como-chegar:presidências:organização:co:modelo-co:programação:comitês-cient:editais:concurso:abepem"/>
    <file name="dp.png" crc="3903465075" seo="true" ref="index:inscrições:ouvinte:datas:submissões:ic:gt:modelo-ic:modelo-gt:evento:anais:dobras:histórico:como-chegar:presidências:organização:co:modelo-co:programação:comitês-cient:editais:concurso:abepem"/>
    <file name="dp_2x.png" crc="514316476" seo="true" ref="index:inscrições:ouvinte:datas:submissões:ic:gt:modelo-ic:modelo-gt:evento:anais:dobras:histórico:como-chegar:presidências:organização:co:modelo-co:programação:comitês-cient:editais:concurso:abepem"/>
    <file name="pgd.png" crc="204641833" seo="true" ref="index:inscrições:ouvinte:datas:submissões:ic:gt:modelo-ic:modelo-gt:evento:anais:dobras:histórico:como-chegar:presidências:organização:co:modelo-co:programação:comitês-cient:editais:concurso:abepem"/>
    <file name="lab d.png" crc="35611211" seo="true" ref="index:inscrições:ouvinte:datas:submissões:ic:gt:modelo-ic:modelo-gt:evento:anais:dobras:histórico:como-chegar:presidências:organização:co:modelo-co:programação:comitês-cient:editais:concurso:abepem"/>
    <file name="lab d_2x.png" crc="3907323764" seo="true" ref="index:inscrições:ouvinte:datas:submissões:ic:gt:modelo-ic:modelo-gt:evento:anais:dobras:histórico:como-chegar:presidências:organização:co:modelo-co:programação:comitês-cient:editais:concurso:abepem"/>
    <file name="labsol.png" crc="155902243" seo="true" ref="index:inscrições:ouvinte:datas:submissões:ic:gt:modelo-ic:modelo-gt:evento:anais:dobras:histórico:como-chegar:presidências:organização:co:modelo-co:programação:comitês-cient:editais:concurso:abepem"/>
    <file name="labsol_2x.png" crc="249928631" seo="true" ref="index:inscrições:ouvinte:datas:submissões:ic:gt:modelo-ic:modelo-gt:evento:anais:dobras:histórico:como-chegar:presidências:organização:co:modelo-co:programação:comitês-cient:editais:concurso:abepem"/>
    <file name="u9507-4.png" crc="4149358932" ref="index:inscrições:ouvinte:datas:submissões:ic:gt:modelo-ic:modelo-gt:evento:anais:dobras:histórico:como-chegar:presidências:organização:co:modelo-co:programação:comitês-cient:editais:concurso:abepem"/>
    <file name="u9507-4_2x.png" crc="4255107951" ref="index:inscrições:ouvinte:datas:submissões:ic:gt:modelo-ic:modelo-gt:evento:anais:dobras:histórico:como-chegar:presidências:organização:co:modelo-co:programação:comitês-cient:editais:concurso:abepem"/>
    <file name="fb branco.png" crc="280469891" seo="true" ref="index:inscrições:ouvinte:datas:submissões:ic:gt:modelo-ic:modelo-gt:evento:anais:dobras:histórico:como-chegar:presidências:organização:co:modelo-co:programação:comitês-cient:editais:concurso:abepem"/>
    <file name="fb branco_2x.png" crc="534209447" seo="true" ref="index:inscrições:ouvinte:datas:submissões:ic:gt:modelo-ic:modelo-gt:evento:anais:dobras:histórico:como-chegar:presidências:organização:co:modelo-co:programação:comitês-cient:editais:concurso:abepem"/>
    <file name="ig branco.png" crc="4184239748" seo="true" ref="index:inscrições:ouvinte:datas:submissões:ic:gt:modelo-ic:modelo-gt:evento:anais:dobras:histórico:como-chegar:presidências:organização:co:modelo-co:programação:comitês-cient:editais:concurso:abepem"/>
    <file name="ig branco_2x.png" crc="104487193" seo="true" ref="index:inscrições:ouvinte:datas:submissões:ic:gt:modelo-ic:modelo-gt:evento:anais:dobras:histórico:como-chegar:presidências:organização:co:modelo-co:programação:comitês-cient:editais:concurso:abepem"/>
    <file name="u8543.png" crc="4259171823" ref="index:inscrições:ouvinte:datas:submissões:ic:gt:modelo-ic:modelo-gt:evento:anais:dobras:histórico:como-chegar:presidências:organização:co:modelo-co:programação:comitês-cient:editais:concurso:abepem"/>
    <file name="u8543_2x.png" crc="268124790" ref="index:inscrições:ouvinte:datas:submissões:ic:gt:modelo-ic:modelo-gt:evento:anais:dobras:histórico:como-chegar:presidências:organização:co:modelo-co:programação:comitês-cient:editais:concurso:abepem"/>
    <file name="u8543-ferr.png" crc="3944570985" ref="index:inscrições:ouvinte:datas:submissões:ic:gt:modelo-ic:modelo-gt:evento:anais:dobras:histórico:como-chegar:presidências:organização:co:modelo-co:programação:comitês-cient:editais:concurso:abepem"/>
    <file name="u8543-ferr_2x.png" crc="3850171985" ref="index:inscrições:ouvinte:datas:submissões:ic:gt:modelo-ic:modelo-gt:evento:anais:dobras:histórico:como-chegar:presidências:organização:co:modelo-co:programação:comitês-cient:editais:concurso:abepem"/>
    <file name="u8541.png" crc="4016061695" ref="index:inscrições:ouvinte:datas:submissões:ic:gt:modelo-ic:modelo-gt:evento:anais:dobras:histórico:como-chegar:presidências:organização:co:modelo-co:programação:comitês-cient:editais:concurso:abepem"/>
    <file name="u8541_2x.png" crc="3935582004" ref="index:inscrições:ouvinte:datas:submissões:ic:gt:modelo-ic:modelo-gt:evento:anais:dobras:histórico:como-chegar:presidências:organização:co:modelo-co:programação:comitês-cient:editais:concurso:abepem"/>
    <file name="u8541-r.png" crc="4066628970" ref="index:inscrições:ouvinte:datas:submissões:ic:gt:modelo-ic:modelo-gt:evento:anais:dobras:histórico:como-chegar:presidências:organização:co:modelo-co:programação:comitês-cient:editais:concurso:abepem"/>
    <file name="u8541-r_2x.png" crc="327303489" ref="index:inscrições:ouvinte:datas:submissões:ic:gt:modelo-ic:modelo-gt:evento:anais:dobras:histórico:como-chegar:presidências:organização:co:modelo-co:programação:comitês-cient:editais:concurso:abepem"/>
    <file name="u8541-fs.png" crc="4205566293" ref="index:inscrições:ouvinte:datas:submissões:ic:gt:modelo-ic:modelo-gt:evento:anais:dobras:histórico:como-chegar:presidências:organização:co:modelo-co:programação:comitês-cient:editais:concurso:abepem"/>
    <file name="u8541-fs_2x.png" crc="4283390145" ref="index:inscrições:ouvinte:datas:submissões:ic:gt:modelo-ic:modelo-gt:evento:anais:dobras:histórico:como-chegar:presidências:organização:co:modelo-co:programação:comitês-cient:editais:concurso:abepem"/>
    <file name="u13440-42.png" crc="148887450" ref="index"/>
    <file name="u13440-4_2x2.png" crc="263837266" ref="index"/>
    <file name="u13422-42.png" crc="4148167142" ref="index"/>
    <file name="u13422-4_2x2.png" crc="4091236846" ref="index"/>
    <file name="u13416-42.png" crc="4024143267" ref="index"/>
    <file name="u13416-4_2x2.png" crc="125681" ref="index"/>
    <file name="u13398-42.png" crc="498419744" ref="index"/>
    <file name="u13398-4_2x2.png" crc="361226346" ref="index"/>
    <file name="u12544-72.png" crc="3800844970" ref="index"/>
    <file name="u12544-7_2x2.png" crc="3958465919" ref="index"/>
    <file name="lab d-crop-u53560.png" crc="4284331766" ref="index:inscrições:ouvinte:datas:submissões:ic:gt:modelo-ic:modelo-gt:evento:anais:dobras:histórico:como-chegar:presidências:organização:co:modelo-co:programação:comitês-cient:editais:concurso:abepem"/>
    <file name="lab d-crop-u53560_2x.png" crc="638811" ref="index:inscrições:ouvinte:datas:submissões:ic:gt:modelo-ic:modelo-gt:evento:anais:dobras:histórico:como-chegar:presidências:organização:co:modelo-co:programação:comitês-cient:editais:concurso:abepem"/>
    <file name="abepem preto-crop-u53448.png" crc="412977295" ref="index:inscrições:ouvinte:datas:submissões:ic:gt:modelo-ic:modelo-gt:evento:anais:dobras:histórico:como-chegar:presidências:organização:co:modelo-co:programação:comitês-cient:editais:concurso:abepem"/>
    <file name="unesp pt112x41.png" crc="495472230" seo="true" ref="index"/>
    <file name="unesp pt112x41_2x.png" crc="3941576220" seo="true" ref="index"/>
    <file name="u13440-43.png" crc="495734531" ref="index"/>
    <file name="u13440-4_2x3.png" crc="155478213" ref="index"/>
    <file name="u13422-43.png" crc="4094151560" ref="index"/>
    <file name="u13422-4_2x3.png" crc="3849970456" ref="index"/>
    <file name="u13416-43.png" crc="4151648815" ref="index"/>
    <file name="u13416-4_2x3.png" crc="477011475" ref="index"/>
    <file name="u13398-43.png" crc="509231982" ref="index"/>
    <file name="u13398-4_2x3.png" crc="4108144041" ref="index"/>
    <file name="left20x29.png" crc="4048350406" seo="true" ref="index"/>
    <file name="left20x29_2x.png" crc="3853299915" seo="true" ref="index"/>
    <file name="right20x29.png" crc="4048350406" seo="true" ref="index"/>
    <file name="right20x29_2x.png" crc="3853299915" seo="true" ref="index"/>
    <file name="patrocínio2662x85.png" crc="87711232" seo="true" ref="index"/>
    <file name="u12544-73.png" crc="3869798850" ref="index"/>
    <file name="u12544-7_2x3.png" crc="3805665791" ref="index"/>
    <file name="abepem98x66.png" crc="3831861458" seo="true" ref="index"/>
    <file name="ativo 2126x46.png" crc="4233139410" seo="true" ref="index"/>
    <file name="ativo 2126x46_2x.png" crc="3777802382" seo="true" ref="index"/>
    <file name="ativo 148x48.png" crc="461229694" seo="true" ref="index"/>
    <file name="ativo 148x48_2x.png" crc="428362331" seo="true" ref="index"/>
    <file name="dp58x37.png" crc="435178601" seo="true" ref="index"/>
    <file name="dp58x37_2x.png" crc="4208583156" seo="true" ref="index"/>
    <file name="pgd59x35.png" crc="4232586926" seo="true" ref="index"/>
    <file name="lab d62x56.png" crc="4149640233" seo="true" ref="index"/>
    <file name="lab d62x56_2x.png" crc="3848928810" seo="true" ref="index"/>
    <file name="labsol56x32.png" crc="4282345320" seo="true" ref="index"/>
    <file name="labsol56x32_2x.png" crc="148534197" seo="true" ref="index"/>
  </folder>
  <file name="index.html" crc="188929754" seo="true" mt="1484279700291" redirect="true"/>
  <file name="inscrições.html" crc="203482683" seo="true" mt="1484279700291" redirect="true"/>
  <file name="ouvinte.html" crc="210633624" seo="true" mt="1484279700291" redirect="true"/>
  <file name="datas.html" crc="83988443" seo="true" mt="1484279700291" redirect="true"/>
  <file name="submissões.html" crc="87375768" seo="true" mt="1484279700291" redirect="true"/>
  <file name="ic.html" crc="470079889" seo="true" mt="1484279700291" redirect="true"/>
  <file name="gt.html" crc="3821849501" seo="true" mt="1484279700291" redirect="true"/>
  <file name="modelo-ic.html" crc="3954664166" seo="true" mt="1484279700291" redirect="true"/>
  <file name="modelo-gt.html" crc="99883600" seo="true" mt="1484279700291" redirect="true"/>
  <file name="evento.html" crc="433245008" seo="true" mt="1484279700291" redirect="true"/>
  <file name="anais.html" crc="4285669101" seo="true" mt="1484279869200" redirect="true"/>
  <file name="dobras.html" crc="4080903032" seo="true" mt="1484279700291" redirect="true"/>
  <file name="histórico.html" crc="3962240339" seo="true" mt="1484279825211" redirect="true"/>
  <file name="como-chegar.html" crc="496404445" seo="true" mt="1484279911769" redirect="true"/>
  <file name="presidências.html" crc="391719808" seo="true" mt="1484279837605" redirect="true"/>
  <file name="organização.html" crc="4091849461" seo="true" mt="1484279700291" redirect="true"/>
  <file name="co.html" crc="486352070" seo="true" mt="1484279700291" redirect="true"/>
  <file name="modelo-co.html" crc="47203697" seo="true" mt="1484279700291" redirect="true"/>
  <file name="programação.html" crc="4221657898" seo="true" mt="1484279700291" redirect="true"/>
  <file name="comitês-cient.html" crc="3960104229" seo="true" mt="1484279700291" redirect="true"/>
  <file name="editais.html" crc="4168575772" seo="true" mt="1484279700291" redirect="true"/>
  <file name="concurso.html" crc="240046430" seo="true" mt="1484279700291" redirect="true"/>
  <file name="abepem.html" crc="466567085" seo="true" mt="1484279700291" redirect="true"/>
</manifest>